{
  "shape": "Rocailles",
  "size": "6/0",
  "colorGroup": "transp. grey, copper",
  "glassGroup": "Transparent",
  "finish": "Lined",
  "dyed": "Non Dyed",
  "galvanized": "Non Galvanized",
  "plating": "Plated",
  "additionalArticleNumber": "331-19001",
  "wholeArticleNumber": "331-19001-6/0-49010",
  "colorNumber": "49010",
  "colorDescription": "transp. grey, copper lined",
  "naturalFinished": "finished",
  "resistance": "4 - low resistance",
  "articleDescription": "Rocailles, round hole, loose",
  "beadId": "331-19001-6_0-49010"
}
