{
  "shape": "Rocailles",
  "size": "10/0",
  "colorGroup": "aquamarine, colour white",
  "glassGroup": "Transparent",
  "finish": "Lined",
  "dyed": "Non Dyed",
  "galvanized": "Non Galvanized",
  "plating": "Plated",
  "additionalArticleNumber": "331-19001",
  "wholeArticleNumber": "331-19001-10/0-65016",
  "colorNumber": "65016",
  "colorDescription": "aquamarine, colour lined white",
  "naturalFinished": "finished",
  "resistance": "5 - very low resistance",
  "articleDescription": "Rocailles, round hole, loose",
  "beadId": "331-19001-10_0-65016"
}
